airignis/__init__.py
airignis/autoevent.py
airignis/duetime.py
airignis/event.py
airignis/exceptions.py
airignis-0.0.4.dist-info/LICENCE
airignis-0.0.4.dist-info/METADATA
airignis-0.0.4.dist-info/NOTICE
airignis-0.0.4.dist-info/WHEEL
airignis-0.0.4.dist-info/top_level.txt
airignis-0.0.4.dist-info/RECORD
