Metadata-Version: 2.1
Name: airignis
Version: 0.0.4
Summary: Looking for a C# familiar package to handle events or looking for a very practical and intuitive way to schedule periodically launching auto event? Then this package is for you.
Home-page: https://github.com/Subvael/Airignis
Author: Subvael
Author-email: Subvael@gmail.com
License: UNKNOWN
Platform: UNKNOWN
Classifier: Programming Language :: Python :: 3
Classifier: Programming Language :: Python :: 3.8
Classifier: Programming Language :: Python :: 3.9
Classifier: Programming Language :: Python :: 3.10
Classifier: License :: OSI Approved :: MIT License
Classifier: Operating System :: OS Independent
Requires-Dist: python-dateutil (==2.7.5)
